{"name":"Get an active task with valid id","id":"get-an-active-task;get-an-active-task-with-valid-id","testSteps":[{"number":1,"description":"Given Get an active task with valid id \"6529449890\"","duration":3,"startTime":"2023-01-20T16:38:27.686+07:00[Asia/Bangkok]","result":"SUCCESS","precondition":false,"level":0,"children":[{"number":2,"description":"Get active task","duration":1,"startTime":"2023-01-20T16:38:27.688+07:00[Asia/Bangkok]","result":"SUCCESS","precondition":false,"level":1}]},{"number":3,"description":"When Send request get an active task","duration":444,"startTime":"2023-01-20T16:38:27.690+07:00[Asia/Bangkok]","result":"SUCCESS","precondition":false,"level":0,"children":[{"number":4,"description":"GET https://api.todoist.com/rest/v2/tasks/6529449890\r","duration":0,"startTime":"2023-01-20T16:38:28.134+07:00[Asia/Bangkok]","result":"SUCCESS","restQuery":{"method":"GET","path":"https://api.todoist.com/rest/v2/tasks/6529449890\r","content":"\r","contentType":"null","requestHeaders":"Authorization\u003dBearer 6cbd35bffb18682aba3874e9563f7f3d0d3b6ada\r\n\t\t\t\tAccept\u003d*/*\r","requestCookies":"\r","responseHeaders":"Content-Type: application/json\r\nContent-Length: 408\r\nConnection: keep-alive\r\nDate: Fri, 20 Jan 2023 09:38:27 GMT\r\nAccess-Control-Allow-Credentials: false\r\nAccess-Control-Allow-Origin: *\r\nReferrer-Policy: strict-origin-when-cross-origin\r\nSet-Cookie: csrf\u003d16bf6d72d67f4ba48571b46939071a6f; Expires\u003dMon, 17-Jan-2033 09:38:27 GMT; Secure; Path\u003d/; SameSite\u003dNone\r\nStrict-Transport-Security: max-age\u003d31536000; includeSubDomains; preload\r\nVary: Accept-Encoding\r\nX-Cache: Miss from cloudfront\r\nVia: 1.1 f9df53a38d19e1a90eab908c0a450470.cloudfront.net (CloudFront)\r\nX-Amz-Cf-Pop: CGK50-P2\r\nX-Amz-Cf-Id: kIuvGH2oka8QP8z3k-D4fWp3VVqx8PIqfQY1NURIQ7FLBQB-vdkyNw\u003d\u003d\r","responseCookies":"csrf\u003d16bf6d72d67f4ba48571b46939071a6f;Path\u003d/;Secure;Expires\u003d1/17/33 9:38 AM;SameSite\u003dNone\r","responseBody":"{\n    \"id\": \"6529449890\",\n    \"assigner_id\": null,\n    \"assignee_id\": null,\n    \"project_id\": \"2306143459\",\n    \"section_id\": null,\n    \"parent_id\": null,\n    \"order\": 1,\n    \"content\": \"GET 1\",\n    \"description\": \"\",\n    \"is_completed\": true,\n    \"labels\": [\n        \n    ],\n    \"priority\": 1,\n    \"comment_count\": 2,\n    \"creator_id\": \"38647742\",\n    \"created_at\": \"2023-01-17T06:25:01.356318Z\",\n    \"due\": null,\n    \"url\": \"https://todoist.com/showTask?id\u003d6529449890\"\n}","statusCode":200},"precondition":false,"level":1}]},{"number":5,"description":"Then Should return status code 200","duration":2,"startTime":"2023-01-20T16:38:28.135+07:00[Asia/Bangkok]","result":"SUCCESS","precondition":false,"level":0},{"number":6,"description":"And Return body should be id \u003d \"6529449890\"","duration":8,"startTime":"2023-01-20T16:38:28.137+07:00[Asia/Bangkok]","result":"SUCCESS","precondition":false,"level":0},{"number":7,"description":"And Validate json schema get an active task","duration":6,"startTime":"2023-01-20T16:38:28.145+07:00[Asia/Bangkok]","result":"SUCCESS","precondition":false,"level":0}],"userStory":{"id":"get-an-active-task","storyName":"Get an active task","path":"classpath:features/Tasks/GetActiveTask.feature","type":"feature"},"featureTag":{"name":"Tasks/Get an active task","type":"feature","displayName":"Tasks/Get an active task"},"title":"Get an active task with valid id","description":"","tags":[{"name":"Tasks","type":"capability","displayName":"Tasks"},{"name":"Tasks/Get an active task","type":"feature","displayName":"Get an active task"},{"name":"GroupProject","type":"tag","displayName":"GroupProject"}],"startTime":"2023-01-20T16:38:27.684+07:00[Asia/Bangkok]","duration":468,"projectKey":"","isManualTestingUpToDate":false,"manual":false,"testSource":"Cucumber","result":"SUCCESS"}